tweetinstone/__init__.py
tweetinstone/capture.py
tweetinstone/file_ops.py
tweetinstone/initialize.py
tweetinstone/main.py
tweetinstone/media_ops.py
tweetinstone/search.py
tweetinstone/text_ops.py
tweetinstone/traversal.py
tweetinstone/version.py
tweetinstone/gui/__init__.py
tweetinstone/gui/main_window.py
tweetinstone/gui/search_window.py
tweetinstone/gui/stylesheet.py
tweetinstone/gui/worker.py
tweetinstone-1.0.1.dist-info/METADATA
tweetinstone-1.0.1.dist-info/WHEEL
tweetinstone-1.0.1.dist-info/entry_points.txt
tweetinstone-1.0.1.dist-info/licenses/LICENSE.txt
tweetinstone-1.0.1.dist-info/RECORD
