Metadata-Version: 2.3
Name: tweetinstone
Version: 1.0.1
Summary: A CLI and GUI tool to automate the capture of tweets in the form they are actually displayed
Project-URL: Homepage, https://tweetinstone.com
Project-URL: Repository, https://github.com/maxdelayer/tweetinstone
Project-URL: Documentation, https://github.com/maxdelayer/tweetinstone/README.md
Project-URL: Issues, https://github.com/maxdelayer/tweetinstone/issues
Project-URL: Tip Jar, https://paypal.me/tweetinstone
Author-email: Max <tweetinstone@protonmail.com>
License-File: LICENSE.txt
Keywords: archive,ffmpeg,screenshot,tweet,twitter
Classifier: Development Status :: 4 - Beta
Classifier: Environment :: Console
Classifier: Intended Audience :: End Users/Desktop
Classifier: Intended Audience :: Legal Industry
Classifier: License :: OSI Approved :: GNU General Public License v3 (GPLv3)
Classifier: Natural Language :: English
Classifier: Operating System :: OS Independent
Classifier: Programming Language :: Python :: 3
Classifier: Topic :: Multimedia :: Graphics :: Capture :: Screen Capture
Classifier: Topic :: Multimedia :: Video :: Conversion
Requires-Python: >=3.8
Requires-Dist: beautifulsoup4>=4.12.2
Requires-Dist: configobj>=5.0.6
Requires-Dist: ffmpeg-python>=0.2.0
Requires-Dist: lxml>=4.9.3
Requires-Dist: pillow>=10.0.0
Requires-Dist: playwright>=1.33.0
Requires-Dist: pyside6>=6.2.4
Requires-Dist: pytest-playwright>=0.3.3
Requires-Dist: yt-dlp>=2023.7.6
